setup.cfg
setup.py
pgop/__init__.py
pgop.egg-info/PKG-INFO
pgop.egg-info/SOURCES.txt
pgop.egg-info/dependency_links.txt
pgop.egg-info/requires.txt
pgop.egg-info/top_level.txt