Metadata-Version: 1.0
Name: pgop
Version: 0.0.4
Summary: Interface module to control Greenwave Reality Lights
Home-page: https://github.com/madmanmatt/pgop
Author: Matt Stang
Author-email: git@stang.im
License: MIT
Platform: UNKNOWN
